README.rst
setup.py
coltron/__init__.py
coltron/crc.py
coltron/utils.py
coltron.egg-info/PKG-INFO
coltron.egg-info/SOURCES.txt
coltron.egg-info/dependency_links.txt
coltron.egg-info/entry_points.txt
coltron.egg-info/requires.txt
coltron.egg-info/top_level.txt
coltron/data/annotation/MotifDictionary.txt
coltron/data/annotation/TFlist_NMid_hg19.txt
coltron/data/annotation/TFlist_NMid_mm9.txt
coltron/data/annotation/VertebratePWMs.txt
coltron/data/annotation/hg18_refseq.ucsc
coltron/data/annotation/hg19_refseq.ucsc
coltron/data/annotation/mm9_refseq.ucsc