Metadata-Version: 1.1
Name: coltron
Version: 1.0.2
Summary: Package for generating and analyzing transcription networks
Home-page: https://github.com/BradnerLab/pipeline
Author: Alex Federation
Author-email: drpolaskijr@gmail.com
License: UNKNOWN
Platform: UNKNOWN
Requires: networkx
Requires: numpy
